cmsplugin_articles
