Metadata-Version: 1.1
Name: cmsplugin-articles
Version: 0.2.2
Summary: Django CMS articles management plugin
Home-page: https://github.com/satyrius/cmsplugin-articles
Author: Anton Egorov
Author-email: anton.egoroff@gmail.com
License: MIT
Platform: OS Independent
Classifier: Development Status :: 5 - Production/Stable
Classifier: Environment :: Web Environment
Classifier: Framework :: Django
Classifier: Intended Audience :: Developers
Classifier: License :: OSI Approved :: MIT License
Classifier: Operating System :: OS Independent
Classifier: Programming Language :: Python
Classifier: Topic :: Communications
Classifier: Topic :: Internet :: WWW/HTTP :: Dynamic Content
Classifier: Topic :: Internet :: WWW/HTTP :: Dynamic Content :: Message Boards
Classifier: Topic :: Internet :: WWW/HTTP :: Site Management
Classifier: Programming Language :: Python :: 2.7
